bunny_m/__init__.py
bunny_m/apps.py
bunny_m/consumer.py
bunny_m/event.py
bunny_m/exceptions.py
bunny_m/generator.py
bunny_m/logger.py
bunny_m/message.py
bunny_m/settings.py
bunny_m/management/__init__.py
bunny_m/management/commands/__init__.py
bunny_m/management/commands/create_bunny_event.py
bunny_m/management/commands/start_all_consumers.py
bunny_m/management/commands/start_consumer.py
bunny_m/providers/__init__.py
bunny_m/providers/connection.py
bunny_m/providers/consumers.py
bunny_m/services/__init__.py
bunny_m/services/base_manager.py
bunny_m/services/consumer.py
bunny_m/services/producer.py
bunny_m/templates/base_consumer_template.py
bunny_m/templates/event_template.py
bunny_m/templates/message_format_template.py
bunny_m/templates/message_template.py
bunny_m/tests/__init__.py
bunny_m/tests/providers/__init__.py
bunny_m/tests/providers/test_connection.py
bunny_m/tests/providers/test_consumers.py
bunny_m/tests/services/__init__.py
bunny_m/tests/services/test_base_manager.py
bunny_m/tests/services/test_consumer.py
bunny_m/tests/services/test_producer.py
django_bunny_m-0.1.3.dist-info/LICENSE
django_bunny_m-0.1.3.dist-info/METADATA
django_bunny_m-0.1.3.dist-info/WHEEL
django_bunny_m-0.1.3.dist-info/top_level.txt
django_bunny_m-0.1.3.dist-info/RECORD
