Metadata-Version: 2.1
Name: django-bunny-m
Version: 0.1.3
Summary: A Django module to RabbitMQ communication
Author: Zwiezda
Author-email: kuba_drapiewski@protonmail.com
License: BSD-3-Clause  # Example license
Classifier: Environment :: Web Environment
Classifier: Framework :: Django
Classifier: Intended Audience :: Developers
Classifier: License :: OSI Approved :: BSD License
Classifier: Operating System :: OS Independent
Classifier: Programming Language :: Python
Classifier: Programming Language :: Python :: 3
Classifier: Programming Language :: Python :: 3 :: Only
Classifier: Programming Language :: Python :: 3.8
Classifier: Programming Language :: Python :: 3.9
Classifier: Programming Language :: Python :: 3.10
Classifier: Programming Language :: Python :: 3.11
Classifier: Programming Language :: Python :: 3.12
Classifier: Topic :: Internet :: WWW/HTTP
Classifier: Topic :: Internet :: WWW/HTTP :: Dynamic Content
Requires-Python: >=3.8
License-File: LICENSE
Requires-Dist: Django >=3.0.0
Requires-Dist: pika >=1.3.0
Requires-Dist: marshmallow >=3.0.0
Requires-Dist: simplejson >=3.0.0
